avalon/__init__.py
avalon/auxiliary.py
avalon/cli.py
avalon/processors.py
avalon/registry.py
avalon/formats/__init__.py
avalon/formats/idmef.py
avalon/formats/linebase.py
avalon/formats/listbase.py
avalon/formats/ext/README.org
avalon/generics/__init__.py
avalon/generics/modelsargs.py
avalon/generics/shortcuts.py
avalon/generics/ext/README.org
avalon/mappings/__init__.py
avalon/mappings/cast.py
avalon/mappings/grpc.py
avalon/mappings/jsoncolumn.py
avalon/mappings/simple.py
avalon/mappings/ext/README.org
avalon/mediums/__init__.py
avalon/mediums/file.py
avalon/mediums/grpc.py
avalon/mediums/httpbase.py
avalon/mediums/kafka.py
avalon/mediums/soap.py
avalon/mediums/sql.py
avalon/mediums/syslogbase.py
avalon/mediums/ext/README.org
avalon/models/__init__.py
avalon/models/rand.py
avalon/models/rflow.py
avalon/models/templates.py
avalon/models/ext/README.org
avalon/models/log/asa.py
avalon/models/log/fortigate.py
avalon/models/log/pptp.py
avalon/models/log/screenon.py
avalon/models/log/snort.py
avalon/models/rflowdata/__init__.py
avalon/models/rflowdata/params.py
avalon_generator-1.1.0.data/data/etc/avalon/metadata-list.sh
avalon_generator-1.1.0.dist-info/LICENSE.org
avalon_generator-1.1.0.dist-info/METADATA
avalon_generator-1.1.0.dist-info/WHEEL
avalon_generator-1.1.0.dist-info/entry_points.txt
avalon_generator-1.1.0.dist-info/top_level.txt
avalon_generator-1.1.0.dist-info/RECORD
